[{"name":"Scream & Shout: 1964 Beatlemania Interviews","number_of_tracks":"12","band_name":"The Beatles","release_date":"N\/A","label":"N\/A","genre":"N\/A"},{"name":"Early Recordings: 1958-1963","number_of_tracks":"29","band_name":"The Beatles","release_date":"2016-04-12T23:00:00Z","label":"N\/A","genre":"N\/A"},{"name":"Retro Songs By The Beatles","number_of_tracks":"15","band_name":"The Beatles","release_date":"2016-04-21T23:00:00Z","label":"N\/A","genre":"N\/A"},{"name":"The Early Years 1958-1963","number_of_tracks":"29","band_name":"The Beatles","release_date":"2015-06-30T23:00:00Z","label":"N\/A","genre":"N\/A"},{"name":"What Is And What Should Never Be (1\/4\/71 Paris Theatre)","number_of_tracks":"1","band_name":"Led Zeppelin","release_date":"2016-09-08T23:00:00Z","label":"N\/A","genre":"N\/A"},{"name":"Communication Breakdown (1\/4\/71 Paris Theatre)","number_of_tracks":"1","band_name":"Led Zeppelin","release_date":"2016-07-29T04:00:00Z","label":"N\/A","genre":"N\/A"},{"name":"Sunshine Woman (14\/4\/69 Rhythm & Blues Session)","number_of_tracks":"1","band_name":"Led Zeppelin","release_date":"2016-08-26T04:00:00Z","label":"N\/A","genre":"N\/A"},{"name":"In Through The Out Door (Deluxe Edition)","number_of_tracks":"14","band_name":"Led Zeppelin","release_date":"2015-07-30","label":"N\/A","genre":"N\/A"},{"name":"Nothing Part 14","number_of_tracks":"1","band_name":"Pink Floyd","release_date":"2016-11-10T00:00:00Z","label":"N\/A","genre":"N\/A"},{"name":"The Early Years, 1967-1972, Cre\/ation","number_of_tracks":"27","band_name":"Pink Floyd","release_date":"2016-11-11T05:00:00Z","label":"N\/A","genre":"N\/A"},{"name":"Grantchester Meadows","number_of_tracks":"1","band_name":"Pink Floyd","release_date":"2016-08-30T23:00:00Z","label":"N\/A","genre":"N\/A"},{"name":"Green is the Colour","number_of_tracks":"1","band_name":"Pink Floyd","release_date":"2016-10-26T04:00:00Z","label":"N\/A","genre":"N\/A"},{"name":"Gone","number_of_tracks":"1","band_name":"The Eagles","release_date":"N\/A","label":"N\/A","genre":"N\/A"},{"name":"Walk on Water - Single","number_of_tracks":"1","band_name":"The Eagles","release_date":"N\/A","label":"N\/A","genre":"N\/A"},{"name":"my year disya","number_of_tracks":"12","band_name":"The Eagles","release_date":"N\/A","label":"N\/A","genre":"N\/A"},{"name":"Smash Hits From the Eagles & the Kestrels","number_of_tracks":"60","band_name":"The Eagles","release_date":"1998-??-??","label":"N\/A","genre":"N\/A"},{"name":"Market Square Heroes (Live)","number_of_tracks":"20","band_name":"Metallica","release_date":"2016-01-04T00:00:00Z","label":"N\/A","genre":"N\/A"},{"name":"Milton Keynes Festival, June 5th, 1993 (Remastered, Live On Broadcasting)","number_of_tracks":"21","band_name":"Metallica","release_date":"2016-08-15T23:00:00Z","label":"N\/A","genre":"N\/A"},{"name":"Velez Sarsfield Stadium, Buenos Aires, Argentina, May 9th, 1993 (Remastered, Live On Broadcasting)","number_of_tracks":"21","band_name":"Metallica","release_date":"2016-10-11T23:00:00Z","label":"N\/A","genre":"N\/A"},{"name":"County Fairgrounds, Middletown, Ny. June 17th, 1994 (Remastered, Live On Broadcasting)","number_of_tracks":"18","band_name":"Metallica","release_date":"2016-10-11T23:00:00Z","label":"N\/A","genre":"N\/A"},{"name":"Anyway Anyhow Anywhere","number_of_tracks":"1","band_name":"The Who","release_date":"2016-11-04T04:00:00Z","label":"N\/A","genre":"N\/A"},{"name":"The Seeker","number_of_tracks":"1","band_name":"The Who","release_date":"2016-03-11T05:00:00Z","label":"N\/A","genre":"N\/A"},{"name":"I'm Free","number_of_tracks":"1","band_name":"The Who","release_date":"N\/A","label":"N\/A","genre":"N\/A"},{"name":"Twenty","number_of_tracks":"12","band_name":"Lynyrd Skynyrd","release_date":"N\/A","label":"N\/A","genre":"N\/A"},{"name":"Sweet Home Alabama Live At Rockpalast","number_of_tracks":"17","band_name":"Lynyrd Skynyrd","release_date":"N\/A","label":"N\/A","genre":"N\/A"},{"name":"Sweet Home Alabama","number_of_tracks":"17","band_name":"Lynyrd Skynyrd","release_date":"2015-06-15T00:00:00Z","label":"N\/A","genre":"N\/A"},{"name":"Second Helping Live from Jacksonville at the Florida Theatre","number_of_tracks":"8","band_name":"Lynyrd Skynyrd","release_date":"2015-10-22T23:00:00Z","label":"N\/A","genre":"N\/A"},{"name":"Perkins Palace, Pasadena, Ca. December 30, 1987 (Remastered) [Live FM Radio Broadcasting]","number_of_tracks":"16","band_name":"Guns n Roses","release_date":"2016-01-21T00:00:00Z","label":"N\/A","genre":"N\/A"},{"name":"Deer Creek Music Center, Noblesville, in. USA, May 28th, 1991","number_of_tracks":"22","band_name":"Guns n Roses","release_date":"2016-01-15T00:00:00Z","label":"N\/A","genre":"N\/A"},{"name":"American Use Your Illusion Tour, 1993 (Remastered) [Live FM Radio Broadcasting]","number_of_tracks":"21","band_name":"Guns n Roses","release_date":"2016-01-20T00:00:00Z","label":"N\/A","genre":"N\/A"},{"name":"Deer Creek Music Center, Noblesville, In. Usa. May 28th, 1991 (Remastered) [Live FM Radio Broadcasting]","number_of_tracks":"22","band_name":"Guns n Roses","release_date":"2016-01-20T00:00:00Z","label":"N\/A","genre":"N\/A"}]
